__init__.py
nupy/__init__.py
nupy/algebra.py
nupy/iterate.py
nupy-0.1.1.dist-info/LICENCE.TXT
nupy-0.1.1.dist-info/METADATA
nupy-0.1.1.dist-info/WHEEL
nupy-0.1.1.dist-info/top_level.txt
nupy-0.1.1.dist-info/RECORD
