Metadata-Version: 1.0
Name: nupy
Version: 0.1.1
Summary: A package for numerical calculus
Home-page: https://github.com/begeistert
Author: Iván Montiel Cardona
Author-email: ivan.montiel.c@gmail.com
License: UNKNOWN
Platform: UNKNOWN
